recency_frequency.py
recency_frequency-0.0.1.dist-info/LICENSE.txt
recency_frequency-0.0.1.dist-info/METADATA
recency_frequency-0.0.1.dist-info/WHEEL
recency_frequency-0.0.1.dist-info/top_level.txt
recency_frequency-0.0.1.dist-info/RECORD
