Metadata-Version: 2.1
Name: recency-frequency
Version: 0.0.1
Summary: Recency + Frequency
Home-page: UNKNOWN
Author: UNKNOWN
Author-email: UNKNOWN
License: UNKNOWN
Platform: UNKNOWN
